alabaster_jupyterhub/__init__.py
alabaster_jupyterhub/_version.py
alabaster_jupyterhub/edit_on_github.html
alabaster_jupyterhub/layout.html
alabaster_jupyterhub/rightsidebar.html
alabaster_jupyterhub/searchbox.html
alabaster_jupyterhub/theme.conf
alabaster_jupyterhub/static/favicon.ico
alabaster_jupyterhub/static/github_logo.png
alabaster_jupyterhub/static/jupyter.css
alabaster_jupyterhub/static/jupyter_logo.png
alabaster_jupyterhub-0.1.8.dist-info/LICENSE
alabaster_jupyterhub-0.1.8.dist-info/WHEEL
alabaster_jupyterhub-0.1.8.dist-info/METADATA
alabaster_jupyterhub-0.1.8.dist-info/RECORD
