Metadata-Version: 2.1
Name: alabaster_jupyterhub
Version: 0.1.8
Summary: The JupyterHub Alabaster theme
Home-page: https://github.com/jupyterhub/alabaster-jupyterhub
License: UNKNOWN
Author: Project Jupyter
Author-email: jupyter@googlegroups.com
Requires-Dist: sphinx >=1.6
Requires-Dist: alabaster
